flux/__init__.py
flux/cache.py
flux/catalogs.py
flux/cli.py
flux/config.py
flux/context_managers.py
flux/domain/__init__.py
flux/domain/events.py
flux/domain/execution_context.py
flux/domain/resource_request.py
flux/domain/schedule.py
flux/encoders.py
flux/errors.py
flux/mcp_server.py
flux/models.py
flux/output_storage.py
flux/schedule_manager.py
flux/secret_managers.py
flux/server.py
flux/servers/models.py
flux/servers/uvicorn_server.py
flux/task.py
flux/tasks.py
flux/utils.py
flux/worker.py
flux/worker_registry.py
flux/workflow.py
flux_core-0.6.0.dist-info/LICENSE
flux_core-0.6.0.dist-info/METADATA
flux_core-0.6.0.dist-info/WHEEL
flux_core-0.6.0.dist-info/entry_points.txt
flux_core-0.6.0.dist-info/RECORD
