Metadata-Version: 2.1
Name: flux-core
Version: 0.6.0
Summary: Flux is a distributed workflow orchestration engine to build stateful and fault-tolerant workflows.
Home-page: https://github.com/edurdias/flux
Author: Eduardo Dias
Author-email: edurdias@gmail.com
Requires-Python: >=3.12,<4.0
Classifier: Programming Language :: Python :: 3
Classifier: Programming Language :: Python :: 3.12
Provides-Extra: postgresql
Requires-Dist: croniter (>=3.0.3,<4.0.0)
Requires-Dist: dill (>=0.3.9,<0.4.0)
Requires-Dist: fastapi (>=0.115.2,<0.116.0)
Requires-Dist: fastmcp (>=2.5.1,<3.0.0)
Requires-Dist: gputil (>=1.4.0,<2.0.0)
Requires-Dist: h11 (>=0.16.0,<0.17.0)
Requires-Dist: httpx-sse (>=0.4.0,<0.5.0)
Requires-Dist: httpx[sse] (>=0.28.1,<0.29.0)
Requires-Dist: psutil (>=7.0.0,<8.0.0)
Requires-Dist: psycopg2-binary (>=2.9.0,<3.0.0) ; extra == "postgresql"
Requires-Dist: pycryptodome (>=3.21.0,<4.0.0)
Requires-Dist: pydantic (>=2.9.2,<3.0.0)
Requires-Dist: pydantic-settings (>=2.6.1,<3.0.0)
Requires-Dist: python-multipart (>=0.0.20,<0.0.21)
Requires-Dist: sqlalchemy (>=2.0.35,<3.0.0)
Requires-Dist: sse-starlette (>=2.3.5,<3.0.0)
Requires-Dist: tomli (>=2.0.2,<3.0.0)
Requires-Dist: types-croniter (>=6.0.0.20250809,<7.0.0.0)
Requires-Dist: types-setuptools (>=80.7.0.20250516,<81.0.0.0)
Requires-Dist: uvicorn (>=0.31.1,<0.32.0)
Project-URL: Repository, https://github.com/edurdias/flux
